{
  "ocr_results": {
    "original_text": "venea mea non est... hu secuetu sanctum",
    "modern_french_text": "ma vigne n'est pas... je suis un saint gardien"
  },
  "identified_keywords": {
    "elements_visuels": [
      "couronne",
      "roi de castille",
      "épée",
      "personnage assis",
      "architecture"
    ],
    "elements_textuels": []
  },
  "statistics": {
    "total_visual_elements": 5,
    "total_textual_elements": 0,
    "total_identified": 5,
    "has_original_text": true,
    "has_modern_translation": true
  }
}