{
  "ocr_results": {
    "original_text": "A mygdala dulces Nature calida et sicca in II mel ius ex eis cuius cortices fri cando se parantur Iuuamentum retardant ebrietatem No cumentum sat Idumis Re emotio nocumen ti cum sale & Vino Citrino",
    "modern_french_text": "Amandes douces, de nature chaude et sèche, sont meilleures de ces écorces lorsqu’on les frotte, elles fournissent un remède retardant l’ivresse. Pas de nuisance significative. L’émotion est nuisible avec du sel et vin citronné."
  },
  "identified_keywords": {
    "elements_visuels": [
      "arbre",
      "panier",
      "architecture",
      "personnage debout",
      "siège",
      "bâton"
    ],
    "elements_textuels": []
  },
  "statistics": {
    "total_visual_elements": 6,
    "total_textual_elements": 0,
    "total_identified": 6,
    "has_original_text": true,
    "has_modern_translation": true
  }
}